Workbook

Sheet Exit Pipeline
A1: recruiter_name | B1: manager_name | C1: full_name | D1: employee_type | E1: employee_id | F1: joining_date | G1: p_o_value | H1: margin | I1: exit_type | J1: company_name | K1: status | L1: tentative_exit_date | M1: BH | N1: Month
A2: Surekha S | B2: Harshavardhan Reddy | C2: CM Siddiq | D2: 6 | E2: C36221448 | F2: 44727 | G2: 48400 | H2: 4400 | I2: Contract Closure | J2: HP | K2: 5 | L2: 46185 | M2: =VLOOKUP(Query2[[#This Row],[company_name]],'Org Mapping'!$B:$I,8,FALSE) -> Jawad Ulla Khan | N2: =TEXT(Query2[[#This Row],[tentative_exit_date]],"mmm'yy") -> Jun'26
A3: Monika Vakati | B3: Jawad Ulla Khan | C3: Deepa Kumari | D3: 2 | E3: C36230946 | F3: 45103 | G3: 32500 | H3: 7500 | I3: Contract Closure | J3: Accenture-voice | K3: 5 | L3: 46198 | M3: =VLOOKUP(Query2[[#This Row],[company_name]],'Org Mapping'!$B:$I,8,FALSE) -> Jawad Ulla Khan | N3: =TEXT(Query2[[#This Row],[tentative_exit_date]],"mmm'yy") -> Jun'26
A4: Sireesha K | B4: Jawad Ulla Khan | C4: Sowmiya Vijayan | D4: 2 | E4: C36230940 | F4: 45091 | G4: 29500 | H4: 4500 | I4: Contract Closure | J4: Accenture_BPO | K4: 5 | L4: 46185 | M4: =VLOOKUP(Query2[[#This Row],[company_name]],'Org Mapping'!$B:$I,8,FALSE) -> Jawad Ulla Khan | N4: =TEXT(Query2[[#This Row],[tentative_exit_date]],"mmm'yy") -> Jun'26
A5: Mouli Roy | B5: Jawad Ulla Khan | C5: Akhilesh Dilip domb | D5: 2 | E5: C36230932 | F5: 45096 | G5: 35046 | H5: 5346 | I5: Resignation | J5: Accenture-voice | K5: 5 | L5: 46177 | M5: =VLOOKUP(Query2[[#This Row],[company_name]],'Org Mapping'!$B:$I,8,FALSE) -> Jawad Ulla Khan | N5: =TEXT(Query2[[#This Row],[tentative_exit_date]],"mmm'yy") -> Jun'26
A6: Javeed Khan | B6: Jawad Ulla Khan | C6: Shivam Anant Pawar | D6: 2 | E6: C36230953 | F6: 45103 | G6: 41290.56 | H6: 6298.56 | I6: Contract Closure | J6: Accenture-voice | K6: 5 | L6: 46197 | M6: =VLOOKUP(Query2[[#This Row],[company_name]],'Org Mapping'!$B:$I,8,FALSE) -> Jawad Ulla Khan | N6: =TEXT(Query2[[#This Row],[tentative_exit_date]],"mmm'yy") -> Jun'26
A7: Sharad Kiran | B7: Jawad Ulla Khan | C7: Angelica Pereira | D7: 2 | E7: C36231170 | F7: 45117 | G7: 37800 | H7: 7800 | I7: Contract Closure | J7: Accenture-voice | K7: 5 | L7: 46212 | M7: =VLOOKUP(Query2[[#This Row],[company_name]],'Org Mapping'!$B:$I,8,FALSE) -> Jawad Ulla Khan | N7: =TEXT(Query2[[#This Row],[tentative_exit_date]],"mmm'yy") -> Jul'26
A8: Mehraj N | B8: Jawad Ulla Khan | C8: T Gireesha | D8: 2 | E8: C36231155 | F8: 45125 | G8: 29734.82 | H8: 4535.82 | I8: Contract Closure | J8: Accenture_BPO | K8: 5 | L8: 46220 | M8: =VLOOKUP(Query2[[#This Row],[company_name]],'Org Mapping'!$B:$I,8,FALSE) -> Jawad Ulla Khan | N8: =TEXT(Query2[[#This Row],[tentative_exit_date]],"mmm'yy") -> Jul'26
A9: Bindushree R | B9: Jawad Ulla Khan | C9: Magimailishi D | D9: 2 | E9: C36231227 | F9: 45131 | G9: 22015.26 | H9: 7015.26 | I9: Contract Closure | J9: Accenture_BPO | K9: 5 | L9: 46226 | M9: =VLOOKUP(Query2[[#This Row],[company_name]],'Org Mapping'!$B:$I,8,FALSE) -> Jawad Ulla Khan | N9: =TEXT(Query2[[#This Row],[tentative_exit_date]],"mmm'yy") -> Jul'26
A10: Bindushree R | B10: Jawad Ulla Khan | C10: Thambadi Sunil Kumar | D10: 2 | E10: C36231217 | F10: 45131 | G10: 41300 | H10: 6300 | I10: Contract Closure | J10: Accenture_BPO | K10: 5 | L10: 46226 | M10: =VLOOKUP(Query2[[#This Row],[company_name]],'Org Mapping'!$B:$I,8,FALSE) -> Jawad Ulla Khan | N10: =TEXT(Query2[[#This Row],[tentative_exit_date]],"mmm'yy") -> Jul'26
A11: Gifty Sunny | B11: Jawad Ulla Khan | C11: Aanchal | D11: 2 | E11: C36231402 | F11: 45134 | G11: 39530 | H11: 6030 | I11: Contract Closure | J11: Accenture_BPO | K11: 5 | L11: 46229 | M11: =VLOOKUP(Query2[[#This Row],[company_name]],'Org Mapping'!$B:$I,8,FALSE) -> Jawad Ulla Khan | N11: =TEXT(Query2[[#This Row],[tentative_exit_date]],"mmm'yy") -> Jul'26
A12: Raja Shekhar | B12: Jawad Ulla Khan | C12: Lakshmi Sri P | D12: 2 | E12: C36231386 | F12: 45139 | G12: 51840 | H12: 8640 | I12: Project Roll Off | J12: Accenture-voice | K12: 5 | L12: 46203 | M12: =VLOOKUP(Query2[[#This Row],[company_name]],'Org Mapping'!$B:$I,8,FALSE) -> Jawad Ulla Khan | N12: =TEXT(Query2[[#This Row],[tentative_exit_date]],"mmm'yy") -> Jun'26
A13: Pradeep S | B13: Monisha R | C13: Krithika R Das | D13: 2 | E13: C36240140 | F13: 45293 | G13: 66950 | H13: 16950 | I13: Project Roll Off | J13: Accenture-voice | K13: 5 | L13: 46203 | M13: =VLOOKUP(Query2[[#This Row],[company_name]],'Org Mapping'!$B:$I,8,FALSE) -> Jawad Ulla Khan | N13: =TEXT(Query2[[#This Row],[tentative_exit_date]],"mmm'yy") -> Jun'26
... A85: Ningappa M Donni | B85: Prathyusha Mangalampalli | C85: Urvashi Juyal | D85: 2 | E85: C36260597 | F85: 46127 | G85: 41300 | H85: 6300 | I85: Bgv Failure | J85: Accenture_BPO | K85: 5 | L85: 46202 | M85: =VLOOKUP(Query2[[#This Row],[company_name]],'Org Mapping'!$B:$I,8,FALSE) -> Jawad Ulla Khan | N85: =TEXT(Query2[[#This Row],[tentative_exit_date]],"mmm'yy") -> Jun'26

Sheet Exit
A1: recruiter_name | B1: manager_name | C1: full_name | D1: employee_type | E1: employee_id | F1: joining_date | G1: p_o_value | H1: margin | I1: exit_type | J1: company_name | K1: status | L1: last_work_day | M1: created_at | N1: BH | O1: Month
A2: Manini S | B2: Deepshikha Nigam | C2: Prithvi M B | D2: 6 | E2: C36190133 | F2: 43486 | G2: 38999.61 | H2: 5666.61 | I2: Contract Closure | J2: HP | K2: 6 | L2: 46043 | M2: 45937 | N2: =VLOOKUP(Query1[[#This Row],[company_name]],'Org Mapping'!$B:$I,8,FALSE) -> Jawad Ulla Khan | O2: =TEXT(Query1[[#This Row],[last_work_day]],"mmm'yy") -> Jan'26
A3: Meenu AM | B3: Meenu AM | C3: Neeraj Kachroo | D3: 7 | E3: C36201494 | F3: 44166 | G3: 75281.8 | H3: 6991.8 | I3: Resignation | J3: ZTE_payroll | K3: 6 | L3: 46127 | M3: 46150 | N3: =VLOOKUP(Query1[[#This Row],[company_name]],'Org Mapping'!$B:$I,8,FALSE) -> TBA | O3: =TEXT(Query1[[#This Row],[last_work_day]],"mmm'yy") -> Apr'26
A4: Meenu AM | B4: Meenu AM | C4: Vikas Kumar | D4: 7 | E4: C36201493 | F4: 44166 | G4: 42207.55 | H4: 3767.55 | I4: Resignation | J4: ZTE_payroll | K4: 6 | L4: 46127 | M4: 46150 | N4: =VLOOKUP(Query1[[#This Row],[company_name]],'Org Mapping'!$B:$I,8,FALSE) -> TBA | O4: =TEXT(Query1[[#This Row],[last_work_day]],"mmm'yy") -> Apr'26
A5: Meenu AM | B5: Meenu AM | C5: Ishwar Chander | D5: 7 | E5: C36201573 | F5: 44166 | G5: 42207.55 | H5: 3767.55 | I5: Resignation | J5: ZTE_payroll | K5: 6 | L5: 46127 | M5: 46150 | N5: =VLOOKUP(Query1[[#This Row],[company_name]],'Org Mapping'!$B:$I,8,FALSE) -> TBA | O5: =TEXT(Query1[[#This Row],[last_work_day]],"mmm'yy") -> Apr'26
A6: Meenu AM | B6: Meenu AM | C6: Seema Sindhwani | D6: 7 | E6: C36201490 | F6: 44166 | G6: 42207.55 | H6: 3767.55 | I6: Resignation | J6: ZTE_payroll | K6: 6 | L6: 46127 | M6: 46150 | N6: =VLOOKUP(Query1[[#This Row],[company_name]],'Org Mapping'!$B:$I,8,FALSE) -> TBA | O6: =TEXT(Query1[[#This Row],[last_work_day]],"mmm'yy") -> Apr'26
A7: Meenu AM | B7: Meenu AM | C7: Neeraj Thakur | D7: 7 | E7: C36201572 | F7: 44166 | G7: 40169.8 | H7: 3529.8 | I7: Resignation | J7: ZTE_payroll | K7: 6 | L7: 46127 | M7: 46150 | N7: =VLOOKUP(Query1[[#This Row],[company_name]],'Org Mapping'!$B:$I,8,FALSE) -> TBA | O7: =TEXT(Query1[[#This Row],[last_work_day]],"mmm'yy") -> Apr'26
A8: Meenu AM | B8: Meenu AM | C8: Karan Dev | D8: 7 | E8: C36210360 | F8: 44237 | G8: 44402.05 | H8: 4012.05 | I8: Resignation | J8: ZTE_payroll | K8: 6 | L8: 46127 | M8: 46150 | N8: =VLOOKUP(Query1[[#This Row],[company_name]],'Org Mapping'!$B:$I,8,FALSE) -> TBA | O8: =TEXT(Query1[[#This Row],[last_work_day]],"mmm'yy") -> Apr'26
A9: Abhishek B | B9: Harshavardhan Reddy | C9: Sushma K | D9: 6 | E9: C36210643 | F9: 44272 | G9: 35685 | H9: 5185 | I9: Contract Closure | J9: HP | K9: 6 | L9: 46127 | M9: 46066 | N9: =VLOOKUP(Query1[[#This Row],[company_name]],'Org Mapping'!$B:$I,8,FALSE) -> Jawad Ulla Khan | O9: =TEXT(Query1[[#This Row],[last_work_day]],"mmm'yy") -> Apr'26
A10: Meenu AM | B10: Meenu AM | C10: Anil Kumar Chawla | D10: 7 | E10: C36211233 | F10: 44298 | G10: 57725.8 | H10: 5335.8 | I10: Resignation | J10: ZTE_payroll | K10: 6 | L10: 46127 | M10: 46150 | N10: =VLOOKUP(Query1[[#This Row],[company_name]],'Org Mapping'!$B:$I,8,FALSE) -> TBA | O10: =TEXT(Query1[[#This Row],[last_work_day]],"mmm'yy") -> Apr'26
A11: Anusha Reddy | B11: Sadhna Shukla | C11: Chennaboina Chinni Krishna | D11: 2 | E11: C36211091 | F11: 44312 | G11: 211327.2 | H11: 48614.2 | I11: Contract Closure | J11: NetApp | K11: 6 | L11: 46146 | M11: 44776 | N11: =VLOOKUP(Query1[[#This Row],[company_name]],'Org Mapping'!$B:$I,8,FALSE) -> Sadhna Shukla | O11: =TEXT(Query1[[#This Row],[last_work_day]],"mmm'yy") -> May'26
A12: Nidhi Tingal | B12: Mehr Hashim | C12: Malladi Rama Subbaiah | D12: 2 | E12: C36211451 | F12: 44340 | G12: 207090 | H12: 109924 | I12: Resignation | J12: FlipkartIT | K12: 6 | L12: 46121 | M12: 46092 | N12: =VLOOKUP(Query1[[#This Row],[company_name]],'Org Mapping'!$B:$I,8,FALSE) -> Mehr Hashim | O12: =TEXT(Query1[[#This Row],[last_work_day]],"mmm'yy") -> Apr'26
A13: Monisha R | B13: Harshavardhan Reddy | C13: Nikitha L | D13: 6 | E13: C36212030 | F13: 44382 | G13: 39253.5 | H13: 5703.5 | I13: Contract Closure | J13: HP | K13: 6 | L13: 46023 | M13: 45736 | N13: =VLOOKUP(Query1[[#This Row],[company_name]],'Org Mapping'!$B:$I,8,FALSE) -> Jawad Ulla Khan | O13: =TEXT(Query1[[#This Row],[last_work_day]],"mmm'yy") -> Jan'26
... A455: Divya Np | B455: Jawad Ulla Khan | C455: Nirbhayee Karankote | D455: 2 | E455: CR3625683 | F455: 45827 | G455: 33150 | H455: 6650 | I455: Resignation | J455: Lenovo 2 | K455: 6 | L455: 46052 | M455: 46022 | N455: =VLOOKUP(Query1[[#This Row],[company_name]],'Org Mapping'!$B:$I,8,FALSE) -> UHG/Lenovo | O455: =TEXT(Query1[[#This Row],[last_work_day]],"mmm'yy") -> Jan'26
A456: Ningappa M Donni | B456: Jawad Ulla Khan | C456: Adnan Shabir Sheikh | D456: 2 | E456: CR3625137 | F456: 45806 | I456: Resignation | J456: Lenovo 2 | K456: 6 | L456: 46125 | M456: 46126 | N456: =VLOOKUP(Query1[[#This Row],[company_name]],'Org Mapping'!$B:$I,8,FALSE) -> UHG/Lenovo | O456: =TEXT(Query1[[#This Row],[last_work_day]],"mmm'yy") -> Apr'26
A457: Nishambika S | B457: Shivam Prasad | C457: Pawan Kumar Yadav | D457: 2 | E457: C36250947 | F457: 45803 | G457: 160000 | H457: 10000 | I457: Conversion | J457: Bread Financials_Support | K457: 6 | L457: 46080 | M457: 45976 | N457: =VLOOKUP(Query1[[#This Row],[company_name]],'Org Mapping'!$B:$I,8,FALSE) -> Sadhna Shukla | O457: =TEXT(Query1[[#This Row],[last_work_day]],"mmm'yy") -> Feb'26
A458: Jamadhagni Geethanjali | B458: Jawad Ulla Khan | C458: Hidayath Pasha | D458: 2 | E458: CR3625631 | F458: 45825 | G458: 36699 | H458: 6650 | I458: Resignation | J458: Lenovo 2 | K458: 6 | L458: 46071 | M458: 46076 | N458: =VLOOKUP(Query1[[#This Row],[company_name]],'Org Mapping'!$B:$I,8,FALSE) -> UHG/Lenovo | O458: =TEXT(Query1[[#This Row],[last_work_day]],"mmm'yy") -> Feb'26
A459: Divya Np | B459: Jawad Ulla Khan | C459: Bikash Chandra Samal | D459: 2 | E459: CR3625553 | F459: 45825 | G459: 39627 | H459: 6650 | I459: Conversion | J459: Lenovo 2 | K459: 6 | L459: 46043 | M459: 46055 | N459: =VLOOKUP(Query1[[#This Row],[company_name]],'Org Mapping'!$B:$I,8,FALSE) -> UHG/Lenovo | O459: =TEXT(Query1[[#This Row],[last_work_day]],"mmm'yy") -> Jan'26
A460: NEHA KUMARI | B460: Jawad Ulla Khan | C460: Apoorva J R | D460: 2 | E460: CR3625556 | F460: 45825 | G460: 34988 | H460: 6650 | I460: Resignation | J460: Lenovo 2 | K460: 6 | L460: 46097 | M460: 46066 | N460: =VLOOKUP(Query1[[#This Row],[company_name]],'Org Mapping'!$B:$I,8,FALSE) -> UHG/Lenovo | O460: =TEXT(Query1[[#This Row],[last_work_day]],"mmm'yy") -> Mar'26
A461: Priyanka Barik | B461: Jawad Ulla Khan | C461: Atul Kumar Singh | D461: 2 | E461: CR3625653 | F461: 45829 | G461: 33489 | H461: 6650 | I461: Resignation | J461: Lenovo 2 | K461: 6 | L461: 46077 | M461: 45966 | N461: =VLOOKUP(Query1[[#This Row],[company_name]],'Org Mapping'!$B:$I,8,FALSE) -> UHG/Lenovo | O461: =TEXT(Query1[[#This Row],[last_work_day]],"mmm'yy") -> Feb'26
A462: Priyanka Barik | B462: Jawad Ulla Khan | C462: Suchana Mondal | D462: 2 | E462: CR3625086 | F462: 45804 | G462: 33675 | H462: 6650 | I462: Termination | J462: Lenovo 2 | K462: 6 | L462: 46059 | M462: 46062 | N462: =VLOOKUP(Query1[[#This Row],[company_name]],'Org Mapping'!$B:$I,8,FALSE) -> UHG/Lenovo | O462: =TEXT(Query1[[#This Row],[last_work_day]],"mmm'yy") -> Feb'26
A463: Mahalakshmi S | B463: Jawad Ulla Khan | C463: Jyoti Singh | D463: 2 | E463: CR3625362 | F463: 45808 | G463: 35681 | H463: 6651 | I463: Resignation | J463: Lenovo 2 | K463: 6 | L463: 46168 | M463: 46162 | N463: =VLOOKUP(Query1[[#This Row],[company_name]],'Org Mapping'!$B:$I,8,FALSE) -> UHG/Lenovo | O463: =TEXT(Query1[[#This Row],[last_work_day]],"mmm'yy") -> May'26
A464: Priyanka Barik | B464: Jawad Ulla Khan | C464: Shradha Patil | D464: 2 | E464: CR3625738 | F464: 45829 | G464: 32017 | H464: 6650 | I464: Resignation | J464: Lenovo 2 | K464: 6 | L464: 46092 | M464: 46063 | N464: =VLOOKUP(Query1[[#This Row],[company_name]],'Org Mapping'!$B:$I,8,FALSE) -> UHG/Lenovo | O464: =TEXT(Query1[[#This Row],[last_work_day]],"mmm'yy") -> Mar'26
A465: Basavaraj B | B465: Jawad Ulla Khan | C465: Arbaz Khan | D465: 2 | E465: CR3625545 | F465: 45827 | G465: 37071.65 | H465: 6649.65 | I465: Resignation | J465: Lenovo 2 | K465: 6 | L465: 46097 | M465: 46070 | N465: =VLOOKUP(Query1[[#This Row],[company_name]],'Org Mapping'!$B:$I,8,FALSE) -> UHG/Lenovo | O465: =TEXT(Query1[[#This Row],[last_work_day]],"mmm'yy") -> Mar'26
A466: Ashwini Jekinakatti | B466: Jawad Ulla Khan | C466: Harshanand Devadas Raykar | D466: 2 | E466: CR3625084 | F466: 45804 | G466: 34189 | H466: 6650 | I466: Resignation | J466: Lenovo 2 | K466: 6 | L466: 46144 | M466: 46146 | N466: =VLOOKUP(Query1[[#This Row],[company_name]],'Org Mapping'!$B:$I,8,FALSE) -> UHG/Lenovo | O466: =TEXT(Query1[[#This Row],[last_work_day]],"mmm'yy") -> May'26
A467: Vaishnavi Shambi | B467: Jawad Ulla Khan | C467: Guha Priya N | D467: 2 | E467: CR3625600 | F467: 45827 | G467: 31822 | H467: 6650 | I467: Resignation | J467: Lenovo 2 | K467: 6 | L467: 46065 | M467: 46073 | N467: =VLOOKUP(Query1[[#This Row],[company_name]],'Org Mapping'!$B:$I,8,FALSE) -> UHG/Lenovo | O467: =TEXT(Query1[[#This Row],[last_work_day]],"mmm'yy") -> Feb'26
A468: Priyanka Barik | B468: Jawad Ulla Khan | C468: Kumar Ankit | D468: 2 | E468: CR3625081 | F468: 45804 | G468: 31822 | H468: 6650 | I468: Resignation | J468: Lenovo 2 | K468: 6 | L468: 46059 | M468: 46059 | N468: =VLOOKUP(Query1[[#This Row],[company_name]],'Org Mapping'!$B:$I,8,FALSE) -> UHG/Lenovo | O468: =TEXT(Query1[[#This Row],[last_work_day]],"mmm'yy") -> Feb'26
... A478: Priyanka Barik | B478: Jawad Ulla Khan | C478: Shrayosee Roy | D478: 2 | E478: CR3625589 | F478: 45827 | G478: 33987 | H478: 6650 | I478: Resignation | J478: Lenovo 2 | K478: 6 | L478: 46023 | M478: 45994 | N478: =VLOOKUP(Query1[[#This Row],[company_name]],'Org Mapping'!$B:$I,8,FALSE) -> UHG/Lenovo | O478: =TEXT(Query1[[#This Row],[last_work_day]],"mmm'yy") -> Jan'26
A479: Basavaraj B | B479: Jawad Ulla Khan | C479: Mohan Kumar M | D479: 2 | E479: CR3625447 | F479: 45825 | I479: Resignation | J479: Lenovo 2 | K479: 6 | L479: 46136 | M479: 46113 | N479: =VLOOKUP(Query1[[#This Row],[company_name]],'Org Mapping'!$B:$I,8,FALSE) -> UHG/Lenovo | O479: =TEXT(Query1[[#This Row],[last_work_day]],"mmm'yy") -> Apr'26
A480: Priyanka Barik | B480: Jawad Ulla Khan | C480: G P Varun | D480: 2 | E480: CR3625615 | F480: 45825 | G480: 39512 | H480: 6650 | I480: Resignation | J480: Lenovo 2 | K480: 6 | L480: 46062 | M480: 46039 | N480: =VLOOKUP(Query1[[#This Row],[company_name]],'Org Mapping'!$B:$I,8,FALSE) -> UHG/Lenovo | O480: =TEXT(Query1[[#This Row],[last_work_day]],"mmm'yy") -> Feb'26
A481: Priyanka Barik | B481: Jawad Ulla Khan | C481: Mohammed Sadiq Mulla | D481: 2 | E481: CR3625661 | F481: 45825 | G481: 35989 | H481: 6650 | I481: Resignation | J481: Lenovo 2 | K481: 6 | L481: 46080 | M481: 45987 | N481: =VLOOKUP(Query1[[#This Row],[company_name]],'Org Mapping'!$B:$I,8,FALSE) -> UHG/Lenovo | O481: =TEXT(Query1[[#This Row],[last_work_day]],"mmm'yy") -> Feb'26
A482: Mohanapriya Mahadevan | B482: Mehr Hashim | C482: Abirami Thamaraiselvan | D482: 2 | E482: C36250950 | F482: 45804 | G482: 250000 | H482: 50000 | I482: Project Roll Off | J482: Hinge Health | K482: 6 | L482: 46091 | M482: 46064 | N482: =VLOOKUP(Query1[[#This Row],[company_name]],'Org Mapping'!$B:$I,8,FALSE) -> Mehr Hashim | O482: =TEXT(Query1[[#This Row],[last_work_day]],"mmm'yy") -> Mar'26
A483: Mamta Prajapati | B483: Jawad Ulla Khan | C483: Chintu Kumar | D483: 2 | E483: CR3625066 | F483: 45804 | G483: 40103.92 | H483: 6650.92 | I483: Resignation | J483: Lenovo 2 | K483: 6 | L483: 46107 | M483: 46115 | N483: =VLOOKUP(Query1[[#This Row],[company_name]],'Org Mapping'!$B:$I,8,FALSE) -> UHG/Lenovo | O483: =TEXT(Query1[[#This Row],[last_work_day]],"mmm'yy") -> Mar'26
A484: Mahalakshmi S | B484: Jawad Ulla Khan | C484: Patan Musharraf Khan | D484: 2 | E484: CR3625006 | F484: 45808 | G484: 31822 | H484: 6650 | I484: Resignation | J484: Lenovo 2 | K484: 6 | L484: 46172 | M484: 46161 | N484: =VLOOKUP(Query1[[#This Row],[company_name]],'Org Mapping'!$B:$I,8,FALSE) -> UHG/Lenovo | O484: =TEXT(Query1[[#This Row],[last_work_day]],"mmm'yy") -> May'26
A485: Basavaraj B | B485: Jawad Ulla Khan | C485: Swami Arpita Vishwanth | D485: 2 | E485: CR3625347 | F485: 45804 | I485: Resignation | J485: Lenovo 2 | K485: 6 | L485: 46135 | M485: 46136 | N485: =VLOOKUP(Query1[[#This Row],[company_name]],'Org Mapping'!$B:$I,8,FALSE) -> UHG/Lenovo | O485: =TEXT(Query1[[#This Row],[last_work_day]],"mmm'yy") -> Apr'26
A486: Basavaraj B | B486: Jawad Ulla Khan | C486: Muhammed Hasan Khan | D486: 2 | E486: CR3625696 | F486: 45827 | G486: 0 | H486: 0 | I486: Resignation | J486: Lenovo 2 | K486: 6 | L486: 46106 | M486: 46129 | N486: =VLOOKUP(Query1[[#This Row],[company_name]],'Org Mapping'!$B:$I,8,FALSE) -> UHG/Lenovo | O486: =TEXT(Query1[[#This Row],[last_work_day]],"mmm'yy") -> Mar'26
A487: Muskan S | B487: Jawad Ulla Khan | C487: Samridhi | D487: 2 | E487: CR3625235 | F487: 45808 | G487: 36558 | H487: 6650 | I487: Resignation | J487: Lenovo 2 | K487: 6 | L487: 46121 | M487: 46121 | N487: =VLOOKUP(Query1[[#This Row],[company_name]],'Org Mapping'!$B:$I,8,FALSE) -> UHG/Lenovo | O487: =TEXT(Query1[[#This Row],[last_work_day]],"mmm'yy") -> Apr'26
A488: Sahil Choudhary | B488: Jawad Ulla Khan | C488: Aman | D488: 2 | E488: CR3625241 | F488: 45808 | G488: 35263 | H488: 6651 | I488: Resignation | J488: Lenovo 2 | K488: 6 | L488: 46168 | M488: 46161 | N488: =VLOOKUP(Query1[[#This Row],[company_name]],'Org Mapping'!$B:$I,8,FALSE) -> UHG/Lenovo | O488: =TEXT(Query1[[#This Row],[last_work_day]],"mmm'yy") -> May'26
A489: Priya b | B489: Jawad Ulla Khan | C489: Kh Aadil Iqbal Wani | D489: 2 | E489: CR3625382 | F489: 45806 | G489: 31822 | H489: 6650 | I489: Resignation | J489: Lenovo 2 | K489: 6 | L489: 46027 | M489: 46038 | N489: =VLOOKUP(Query1[[#This Row],[company_name]],'Org Mapping'!$B:$I,8,FALSE) -> UHG/Lenovo | O489: =TEXT(Query1[[#This Row],[last_work_day]],"mmm'yy") -> Jan'26
A490: Mahalakshmi S | B490: Jawad Ulla Khan | C490: Veeresh | D490: 2 | E490: CR3625715 | F490: 45829 | G490: 33489 | H490: 6650 | I490: Resignation | J490: Lenovo 2 | K490: 6 | L490: 46070 | M490: 45965 | N490: =VLOOKUP(Query1[[#This Row],[company_name]],'Org Mapping'!$B:$I,8,FALSE) -> UHG/Lenovo | O490: =TEXT(Query1[[#This Row],[last_work_day]],"mmm'yy") -> Feb'26
A491: Sahil Choudhary | B491: Jawad Ulla Khan | C491: Mohammed Zaid M Mulla | D491: 2 | E491: CR3625498 | F491: 45827 | G491: 31822 | H491: 6650 | I491: Resignation | J491: Lenovo 2 | K491: 6 | L491: 46080 | M491: 46066 | N491: =VLOOKUP(Query1[[#This Row],[company_name]],'Org Mapping'!$B:$I,8,FALSE) -> UHG/Lenovo | O491: =TEXT(Query1[[#This Row],[last_work_day]],"mmm'yy") -> Feb'26
A492: Basavaraj B | B492: Jawad Ulla Khan | C492: Aasif Jaffer | D492: 2 | E492: CR3625059 | F492: 45804 | G492: 43029 | H492: 6650 | I492: Resignation | J492: Lenovo 2 | K492: 6 | L492: 46054 | M492: 46054 | N492: =VLOOKUP(Query1[[#This Row],[company_name]],'Org Mapping'!$B:$I,8,FALSE) -> UHG/Lenovo | O492: =TEXT(Query1[[#This Row],[last_work_day]],"mmm'yy") -> Feb'26
A493: Ningappa M Donni | B493: Jawad Ulla Khan | C493: Sourav Saha | D493: 2 | E493: CR3625058 | F493: 45804 | G493: 70134.92 | H493: 6650.92 | I493: Conversion | J493: Lenovo 2 | K493: 6 | L493: 46048 | M493: 46055 | N493: =VLOOKUP(Query1[[#This Row],[company_name]],'Org Mapping'!$B:$I,8,FALSE) -> UHG/Lenovo | O493: =TEXT(Query1[[#This Row],[last_work_day]],"mmm'yy") -> Jan'26
A494: Mahalakshmi S | B494: Jawad Ulla Khan | C494: Aishwarya H Kounte | D494: 2 | E494: CR3625056 | F494: 45804 | G494: 32850 | H494: 6650 | I494: Resignation | J494: Lenovo 2 | K494: 6 | L494: 46058 | M494: 46058 | N494: =VLOOKUP(Query1[[#This Row],[company_name]],'Org Mapping'!$B:$I,8,FALSE) -> UHG/Lenovo | O494: =TEXT(Query1[[#This Row],[last_work_day]],"mmm'yy") -> Feb'26
A495: Jamadhagni Geethanjali | B495: Jawad Ulla Khan | C495: J Mohammed Saad | D495: 2 | E495: CR3625055 | F495: 45804 | G495: 32655 | H495: 6650 | I495: Resignation | J495: Lenovo 2 | K495: 6 | L495: 46087 | M495: 46087 | N495: =VLOOKUP(Query1[[#This Row],[company_name]],'Org Mapping'!$B:$I,8,FALSE) -> UHG/Lenovo | O495: =TEXT(Query1[[#This Row],[last_work_day]],"mmm'yy") -> Mar'26
A496: Jamadhagni Geethanjali | B496: Jawad Ulla Khan | C496: Priyanka S Salimani | D496: 2 | E496: CR3625757 | F496: 45839 | G496: 37336 | H496: 6650 | I496: Resignation | J496: Lenovo 2 | K496: 6 | L496: 46120 | M496: 46120 | N496: =VLOOKUP(Query1[[#This Row],[company_name]],'Org Mapping'!$B:$I,8,FALSE) -> UHG/Lenovo | O496: =TEXT(Query1[[#This Row],[last_work_day]],"mmm'yy") -> Apr'26
A497: Jamadhagni Geethanjali | B497: Jawad Ulla Khan | C497: Pankaj Chavan | D497: 2 | E497: CR3625713 | F497: 45829 | G497: 33150 | H497: 6650 | I497: Resignation | J497: Lenovo 2 | K497: 6 | L497: 46114 | M497: 46085 | N497: =VLOOKUP(Query1[[#This Row],[company_name]],'Org Mapping'!$B:$I,8,FALSE) -> UHG/Lenovo | O497: =TEXT(Query1[[#This Row],[last_work_day]],"mmm'yy") -> Apr'26
... A1059: Shahid Afridi | B1059: Jawad u | C1059: Abhishek Gupta | D1059: 2 | E1059: C36260915 | F1059: 46169 | G1059: 50700 | H1059: 7366.67 | I1059: Absconded | J1059: HP | K1059: 6 | L1059: 46175 | M1059: 46175 | N1059: =VLOOKUP(Query1[[#This Row],[company_name]],'Org Mapping'!$B:$I,8,FALSE) -> Jawad Ulla Khan | O1059: =TEXT(Query1[[#This Row],[last_work_day]],"mmm'yy") -> Jun'26

Sheet Org Mapping
A1: Status | B1: Client | D1: KAM | E1: DL | F1: Team Name | G1: HRBP | H1: Domain | I1: Business Head | J1: SGN Cohort
B2: Adobe | D2: Sadhna Shukla | E2: Manjunath R | F2: Voyagers | G2: =_xlfn.IFNA(VLOOKUP(B2,O:P,2,FALSE),"TBA") -> TBA | H2: Captive | I2: Sadhna Shukla | J2: Growth
B3: Airbus | D3: Jeevan Ram | E3: Sandipta P | F3: Voyagers | G3: =_xlfn.IFNA(VLOOKUP(B3,O:P,2,FALSE),"TBA") -> TBA | H3: Captive | I3: Mehr Hashim | J3: Growth
B4: Alliance Data | D4: Sushma K M | E4: Manjunath R | F4: Voyagers | G4: =_xlfn.IFNA(VLOOKUP(B4,O:P,2,FALSE),"TBA") -> TBA | H4: Captive | I4: Sadhna Shukla | J4: Growth
B5: Amazon | D5: Jeevan Ram | E5: Sandipta P | F5: Voyagers | G5: =_xlfn.IFNA(VLOOKUP(B5,O:P,2,FALSE),"TBA") -> TBA | H5: Captive | I5: Mehr Hashim | J5: Growth
B6: Analog Devices | D6: Bollamma PA | E6: Sandipta P | F6: Voyagers | G6: =_xlfn.IFNA(VLOOKUP(B6,O:P,2,FALSE),"TBA") -> TBA | H6: Captive | I6: Mehr Hashim | J6: Growth
B7: ANZ | D7: TBA | E7: Goutham Raj | F7: Champions | G7: =_xlfn.IFNA(VLOOKUP(B7,O:P,2,FALSE),"TBA") -> TBA | H7: Captive | I7: TBA | J7: Growth
B8: Atkins | D8: Kshama V Bhat | E8: Santhosh G | F8: Anuradha | G8: =_xlfn.IFNA(VLOOKUP(B8,O:P,2,FALSE),"TBA") -> TBA | H8: Captive | I8: Anuradha | J8: Growth
B9: Backbase | D9: Deepak Desai | F9: Voyagers | G9: =_xlfn.IFNA(VLOOKUP(B9,O:P,2,FALSE),"TBA") -> TBA | H9: Captive | I9: Deepak Desai | J9: Growth
B10: Black and Veatch | D10: TBA | E10: Aranza Dubey | F10: Voyagers | G10: =_xlfn.IFNA(VLOOKUP(B10,O:P,2,FALSE),"TBA") -> TBA | H10: Captive | I10: TBA | J10: Growth
B11: BOSCH_COE | D11: TBA | F11: Champions | G11: =_xlfn.IFNA(VLOOKUP(B11,O:P,2,FALSE),"TBA") -> TBA | H11: Captive | I11: TBA | J11: Growth
B12: BSH | D12: Saravanan P | F12: Champions | G12: =_xlfn.IFNA(VLOOKUP(B12,O:P,2,FALSE),"TBA") -> TBA | H12: Captive | I12: Deepak Desai | J12: Growth
B13: Celestica | D13: Shailesh Gangwar | E13: Manjunath R | F13: Voyagers | G13: =_xlfn.IFNA(VLOOKUP(B13,O:P,2,FALSE),"TBA") -> TBA | H13: Captive | I13: Sadhna Shukla | J13: Growth
B14: CenturyLink Technologies India Pvt.Ltd | D14: Joyesh Banerjee | F14: Anuradha | G14: =_xlfn.IFNA(VLOOKUP(B14,O:P,2,FALSE),"TBA") -> TBA | H14: Captive | I14: Anuradha | J14: Growth
B15: CH Robinson | D15: Kshama V Bhat | E15: Anuradha Murty | F15: Anuradha | G15: =_xlfn.IFNA(VLOOKUP(B15,O:P,2,FALSE),"TBA") -> TBA | H15: Captive | I15: Anuradha | J15: Growth
B16: Cleartrip | D16: Jeevan Ram | E16: Sandipta P | F16: Voyagers | G16: =_xlfn.IFNA(VLOOKUP(B16,O:P,2,FALSE),"TBA") -> TBA | H16: Captive | I16: Mehr Hashim | J16: Growth
B17: CME | D17: Joyesh Banerjee | E17: Santhosh G | F17: Anuradha | G17: =_xlfn.IFNA(VLOOKUP(B17,O:P,2,FALSE),"TBA") -> TBA | H17: Captive | I17: Anuradha | J17: Growth
B18: CME_C2H | D18: Joyesh Banerjee | E18: Santhosh G | F18: Anuradha | G18: =_xlfn.IFNA(VLOOKUP(B18,O:P,2,FALSE),"TBA") -> TBA | H18: Captive | I18: Anuradha | J18: Strategic
B19: Cred | D19: Bollamma PA | F19: Voyagers | G19: =_xlfn.IFNA(VLOOKUP(B19,O:P,2,FALSE),"TBA") -> TBA | H19: Captive | I19: Mehr Hashim | J19: Growth
B20: Danfoss | D20: Sushma K M | E20: Manjunath R | F20: Voyagers | G20: =_xlfn.IFNA(VLOOKUP(B20,O:P,2,FALSE),"TBA") -> TBA | H20: Captive | I20: Sadhna Shukla | J20: Growth
B21: DBS bank | D21: Kshama V Bhat | E21: Shilpa P | F21: Champions | G21: =_xlfn.IFNA(VLOOKUP(B21,O:P,2,FALSE),"TBA") -> TBA | H21: Captive | I21: Anuradha | J21: Growth
B22: Decathlon | D22: TBA | E22: Tara VR | F22: Catalyst | G22: =_xlfn.IFNA(VLOOKUP(B22,O:P,2,FALSE),"TBA") -> TBA | H22: Captive | I22: TBA | J22: New
B23: Dentsu | D23: TBA | E23: Frederick | F23: Nirmit | G23: =_xlfn.IFNA(VLOOKUP(B23,O:P,2,FALSE),"TBA") -> TBA | H23: Captive | I23: TBA | J23: Growth
B24: Diebold Nixdorf | D24: Sonia Sabnani | F24: Nirmit | G24: =_xlfn.IFNA(VLOOKUP(B24,O:P,2,FALSE),"TBA") -> TBA | H24: Captive | I24: (Sonia/Dikshitha) | J24: Growth
B25: Ecolabs | D25: TBA | E25: Goutham Raj | F25: Voyagers | G25: =_xlfn.IFNA(VLOOKUP(B25,O:P,2,FALSE),"TBA") -> TBA | H25: Captive | I25: TBA | J25: Growth
B26: Ellucian | D26: Surya S | E26: Anuradha Murty | F26: Anuradha | G26: =_xlfn.IFNA(VLOOKUP(B26,O:P,2,FALSE),"TBA") -> TBA | H26: Captive | I26: Anuradha | J26: Growth
B27: FlipkartIT | D27: Deepashree | E27: Sandipta P | F27: Voyagers | G27: =_xlfn.IFNA(VLOOKUP(B27,O:P,2,FALSE),"TBA") -> TBA | H27: Captive | I27: Mehr Hashim | J27: Strategic
B28: Fortinet | D28: Sujith AK | E28: Dipika Saha | F28: Voyagers | G28: =_xlfn.IFNA(VLOOKUP(B28,O:P,2,FALSE),"TBA") -> TBA | H28: Captive | I28: Sadhna Shukla | J28: New
B29: Google | D29: Jeevan Ram | E29: Sandipta P | F29: Voyagers | G29: =_xlfn.IFNA(VLOOKUP(B29,O:P,2,FALSE),"TBA") -> TBA | H29: Captive | I29: Mehr Hashim | J29: Growth
B30: Grant Thornton | D30: TBA | E30: Santhosh G | F30: Champions | G30: =_xlfn.IFNA(VLOOKUP(B30,O:P,2,FALSE),"TBA") -> TBA | H30: Captive | I30: TBA | J30: Growth
B31: Hinge Health | D31: Bollamma PA | E31: Sandipta P | F31: Voyagers | G31: =_xlfn.IFNA(VLOOKUP(B31,O:P,2,FALSE),"TBA") -> TBA | H31: Captive | I31: Mehr Hashim | J31: Growth
B32: Incture | D32: TBA | F32: Voyagers | G32: =_xlfn.IFNA(VLOOKUP(B32,O:P,2,FALSE),"TBA") -> TBA | H32: Captive | I32: TBA | J32: Growth
B33: Infinx_Champ | D33: TBA | E33: Santhosh G | F33: Champions | G33: =_xlfn.IFNA(VLOOKUP(B33,O:P,2,FALSE),"TBA") -> TBA | H33: Captive | I33: TBA | J33: Growth
B34: JLL | D34: Surya S | E34: Dipika Saha | F34: Anuradha | G34: =_xlfn.IFNA(VLOOKUP(B34,O:P,2,FALSE),"TBA") -> TBA | H34: Captive | I34: Anuradha | J34: Growth
B35: JLL Routing | D35: Surya S | E35: Dipika Saha | F35: Anuradha | G35: =_xlfn.IFNA(VLOOKUP(B35,O:P,2,FALSE),"TBA") -> TBA | H35: Captive | I35: Anuradha | J35: Growth
B36: Johnson Electric | D36: Sushma K M | E36: Manjunath R | F36: Voyagers | G36: =_xlfn.IFNA(VLOOKUP(B36,O:P,2,FALSE),"TBA") -> TBA | H36: Captive | I36: Sadhna Shukla | J36: Growth
B37: Kimberly Clark | D37: TBA | E37: Dikshita Sehgal | F37: Nirmit | G37: =_xlfn.IFNA(VLOOKUP(B37,O:P,2,FALSE),"TBA") -> TBA | H37: Captive | I37: TBA | J37: Growth
B38: KMART | D38: TBA | F38: Avengers | G38: =_xlfn.IFNA(VLOOKUP(B38,O:P,2,FALSE),"TBA") -> TBA | H38: Captive | I38: Jawad Ulla Khan | J38: Growth
B39: Koch Industries | D39: Joyesh Banerjee | E39: Santhosh G | F39: Anuradha | G39: =_xlfn.IFNA(VLOOKUP(B39,O:P,2,FALSE),"TBA") -> TBA | H39: Captive | I39: Anuradha | J39: Growth
B40: KOCH_COE | D40: Joyesh Banerjee | E40: Santhosh G | F40: Catalyst | G40: =_xlfn.IFNA(VLOOKUP(B40,O:P,2,FALSE),"TBA") -> TBA | H40: Captive | I40: Anuradha | J40: Growth
B41: Lam Research | D41: Sadhna Shukla | F41: Voyagers | G41: =_xlfn.IFNA(VLOOKUP(B41,O:P,2,FALSE),"TBA") -> TBA | H41: Captive | I41: Sadhna Shukla | J41: Growth
B42: Lowes | D42: Deepashree | E42: Sandipta P | F42: Voyagers | G42: =_xlfn.IFNA(VLOOKUP(B42,O:P,2,FALSE),"TBA") -> TBA | H42: Captive | I42: Mehr Hashim | J42: Growth
B43: Lumen | D43: Joyesh Banerjee | E43: Dipika Saha | F43: Anuradha | G43: =_xlfn.IFNA(VLOOKUP(B43,O:P,2,FALSE),"TBA") -> TBA | H43: Captive | I43: Anuradha | J43: Growth
B44: Mercedes benz | D44: TBA | F44: Champions | G44: =_xlfn.IFNA(VLOOKUP(B44,O:P,2,FALSE),"TBA") -> TBA | H44: Captive | I44: TBA | J44: Growth
B45: MercedesBenz-DTICI | D45: TBA | F45: Champions | G45: =_xlfn.IFNA(VLOOKUP(B45,O:P,2,FALSE),"TBA") -> TBA | H45: Captive | I45: TBA | J45: Growth
B46: Moder Solutions | D46: TBA | E46: Chiranjeev Desai | F46: Catalyst | G46: =_xlfn.IFNA(VLOOKUP(B46,O:P,2,FALSE),"TBA") -> TBA | H46: Captive | I46: Prathap Sagar | J46: Growth
B47: Monsanto | D47: TBA | F47: Champions | G47: =_xlfn.IFNA(VLOOKUP(B47,O:P,2,FALSE),"TBA") -> TBA | H47: Captive | I47: TBA | J47: Growth
B48: NetApp | D48: Sushma K M | E48: Dipika Saha | F48: Voyagers | G48: =_xlfn.IFNA(VLOOKUP(B48,O:P,2,FALSE),"TBA") -> TBA | H48: Captive | I48: Sadhna Shukla | J48: Growth
B49: News Corp / NTS India | D49: TBA | F49: Nirmit | G49: =_xlfn.IFNA(VLOOKUP(B49,O:P,2,FALSE),"TBA") -> TBA | H49: Captive | I49: TBA | J49: Growth
B50: Nexteer Automotives | D50: Surya S | E50: Anuradha Murty | F50: Anuradha | G50: =_xlfn.IFNA(VLOOKUP(B50,O:P,2,FALSE),"TBA") -> TBA | H50: Captive | I50: Anuradha | J50: Growth
B51: Northern Trust | D51: Kshama V Bhat | E51: Anuradha Murty | F51: Anuradha | G51: =_xlfn.IFNA(VLOOKUP(B51,O:P,2,FALSE),"TBA") -> TBA | H51: Captive | I51: Anuradha | J51: Growth
B52: Novartis | D52: Kshama V Bhat | E52: Anuradha Murty | F52: Anuradha | G52: =_xlfn.IFNA(VLOOKUP(B52,O:P,2,FALSE),"TBA") -> TBA | H52: Captive | I52: Anuradha | J52: Growth
B53: OSBI | D53: Kshama V Bhat | E53: Santhosh G | F53: Anuradha | G53: =_xlfn.IFNA(VLOOKUP(B53,O:P,2,FALSE),"TBA") -> TBA | H53: Captive | I53: Anuradha | J53: Growth
B54: OTIS | D54: TBA | E54: Sandipta P | F54: Voyagers | G54: =_xlfn.IFNA(VLOOKUP(B54,O:P,2,FALSE),"TBA") -> TBA | H54: Captive | I54: TBA | J54: Growth
B55: Pure Storage | D55: Bollamma PA | E55: Sandipta P | F55: Voyagers | G55: =_xlfn.IFNA(VLOOKUP(B55,O:P,2,FALSE),"TBA") -> TBA | H55: Captive | I55: Mehr Hashim | J55: Growth
B56: Rapid7 | D56: TBA | E56: Dipika Saha | F56: Voyagers | G56: =_xlfn.IFNA(VLOOKUP(B56,O:P,2,FALSE),"TBA") -> TBA | H56: Captive | I56: TBA | J56: Growth
B57: Sandoz | D57: Kshama V Bhat | F57: Anuradha | G57: =_xlfn.IFNA(VLOOKUP(B57,O:P,2,FALSE),"TBA") -> TBA | H57: captive | I57: Anuradha | J57: Growth
B58: Shell | D58: Bollamma PA | E58: Sandipta P | F58: Voyagers | G58: =_xlfn.IFNA(VLOOKUP(B58,O:P,2,FALSE),"TBA") -> TBA | H58: Captive | I58: Mehr Hashim | J58: Growth
B59: Socgen | D59: Surya S | E59: Menaka Prasad | F59: Anuradha | G59: =_xlfn.IFNA(VLOOKUP(B59,O:P,2,FALSE),"TBA") -> TBA | H59: Captive | I59: Anuradha | J59: Strategic
B60: Societe Generale | D60: Surya S | E60: Menaka Prasad | F60: Anuradha | G60: =_xlfn.IFNA(VLOOKUP(B60,O:P,2,FALSE),"TBA") -> TBA | H60: Captive | I60: Anuradha | J60: Growth
B61: Target | D61: Kshama V Bhat | E61: Anuradha | F61: Anuradha | G61: =_xlfn.IFNA(VLOOKUP(B61,O:P,2,FALSE),"TBA") -> TBA | H61: Captive | I61: Anuradha | J61: Growth
B62: Thomson Reuters | D62: Shailesh Gangwar | E62: Manjunath R | F62: Voyagers | G62: =_xlfn.IFNA(VLOOKUP(B62,O:P,2,FALSE),"TBA") -> TBA | H62: Captive | I62: Sadhna Shukla | J62: Growth
B63: Verifone | D63: Surya S | E63: Dipika Saha | F63: Anuradha | G63: =_xlfn.IFNA(VLOOKUP(B63,O:P,2,FALSE),"TBA") -> TBA | H63: Captive | I63: Anuradha | J63: New
B64: Veritas | D64: Sushma K M | E64: Manjunath R | F64: Voyagers | G64: =_xlfn.IFNA(VLOOKUP(B64,O:P,2,FALSE),"TBA") -> TBA | H64: Captive | I64: Sadhna Shukla | J64: Growth
B65: VISA | D65: Dikshita Sehgal | E65: Dhaval patel | G65: =_xlfn.IFNA(VLOOKUP(B65,O:P,2,FALSE),"TBA") -> TBA | H65: Captive | I65: (Sonia/Dikshitha) | J65: Growth
B66: VMware | D66: Sadhna Shukla | E66: Manjunath R | F66: Voyagers | G66: =_xlfn.IFNA(VLOOKUP(B66,O:P,2,FALSE),"TBA") -> TBA | H66: Captive | I66: Sadhna Shukla | J66: Growth
B67: Wartsila | D67: Sushma K M | E67: Anuradha | F67: Voyagers | G67: =_xlfn.IFNA(VLOOKUP(B67,O:P,2,FALSE),"TBA") -> TBA | H67: Captive | I67: Sadhna Shukla | J67: Growth
B68: Wolters Kluwer | D68: Sonia Sabnani | F68: Nirmit | G68: =_xlfn.IFNA(VLOOKUP(B68,O:P,2,FALSE),"TBA") -> TBA | H68: Captive | I68: (Sonia/Dikshitha) | J68: Growth
B69: Wolters Kluwer-India | D69: Sonia Sabnani | F69: Nirmit | G69: =_xlfn.IFNA(VLOOKUP(B69,O:P,2,FALSE),"TBA") -> TBA | H69: Captive | I69: (Sonia/Dikshitha) | J69: Growth
B70: WSP | D70: Kshama V Bhat | F70: Anuradha | G70: =_xlfn.IFNA(VLOOKUP(B70,O:P,2,FALSE),"TBA") -> TBA | H70: Captive | I70: Anuradha | J70: Growth
B71: Wurth IT | D71: Kshama V Bhat | F71: Anuradha | G71: =_xlfn.IFNA(VLOOKUP(B71,O:P,2,FALSE),"TBA") -> TBA | H71: Captive | I71: Anuradha | J71: Growth
B72: Xellia Pharma | D72: Sadhna Shukla | E72: Dipika Saha | F72: Voyagers | G72: =_xlfn.IFNA(VLOOKUP(B72,O:P,2,FALSE),"TBA") -> TBA | H72: Captive | I72: Sadhna Shukla | J72: New
B73: Xylem INC | D73: Sadhna Shukla | E73: Aranza Dubey | F73: Voyagers | G73: =_xlfn.IFNA(VLOOKUP(B73,O:P,2,FALSE),"TBA") -> TBA | H73: Captive | I73: Sadhna Shukla | J73: Growth
B74: Zebra Technologies Corporation | D74: TBA | E74: Manjunath R | F74: Voyagers | G74: =_xlfn.IFNA(VLOOKUP(B74,O:P,2,FALSE),"TBA") -> TBA | H74: Captive | I74: TBA | J74: ITES
B75: ZebraTechnologies | D75: TBA | E75: Justin Dsilva | F75: Voyagers | G75: =_xlfn.IFNA(VLOOKUP(B75,O:P,2,FALSE),"TBA") -> TBA | H75: Captive | I75: TBA | J75: Growth
A76: Smithesh | B76: Deloitte Mercedes Benz | D76: Saravanan P | F76: Nirmit | G76: =_xlfn.IFNA(VLOOKUP(B76,O:P,2,FALSE),"TBA") -> TBA | H76: Captive | I76: Deepak Desai | J76: Growth
B77: L&T Technology services Pvt Ltd | D77: TBA | F77: Deepak Desai | G77: =_xlfn.IFNA(VLOOKUP(B77,O:P,2,FALSE),"TBA") -> TBA | H77: Captive | I77: TBA | J77: Growth
A78: Smithesh | B78: Arcelor Mittal | D78: Deepak Desai | E78: Manjunath R | F78: Nirmit | G78: =_xlfn.IFNA(VLOOKUP(B78,O:P,2,FALSE),"TBA") -> TBA | H78: Captive | I78: Deepak Desai | J78: New
B79: Accenture_BPO | D79: Prathyusha Mangalampalli | E79: Prathyusha Mangalampalli | F79: Avengers | G79: =_xlfn.IFNA(VLOOKUP(B79,O:P,2,FALSE),"TBA") -> TBA | H79: ITES | I79: Jawad Ulla Khan | J79: ITES
B80: Accenture-voice | D80: Prathyusha Mangalampalli | E80: Prathyusha Mangalampalli | F80: Avengers | G80: =_xlfn.IFNA(VLOOKUP(B80,O:P,2,FALSE),"TBA") -> TBA | H80: ITES | I80: Jawad Ulla Khan | J80: ITES
B81: Amadeus Software | D81: Jawad Ulla Khan | E81: Prathyusha Mangalampalli | F81: Anuradha | G81: =_xlfn.IFNA(VLOOKUP(B81,O:P,2,FALSE),"TBA") -> TBA | H81: ITES | I81: Jawad Ulla Khan | J81: Growth
B82: ANZ OPS | D82: TBA | E82: Santhosh G | F82: Champions | G82: =_xlfn.IFNA(VLOOKUP(B82,O:P,2,FALSE),"TBA") -> TBA | H82: ITES | I82: TBA | J82: ITES
B83: Clean Harbors_ITES | D83: Prathyusha Mangalampalli | E83: Prathyusha Mangalampalli | F83: Avengers | G83: =_xlfn.IFNA(VLOOKUP(B83,O:P,2,FALSE),"TBA") -> TBA | H83: ITES | I83: Jawad Ulla Khan | J83: ITES
B84: Flipkart | D84: Deepashree | E84: Sandipta P | F84: Voyagers | G84: =_xlfn.IFNA(VLOOKUP(B84,O:P,2,FALSE),"TBA") -> TBA | H84: ITES | I84: Mehr Hashim | J84: Strategic
B85: FLUENCE ENERGY - PAYROLL | D85: Priyakanta Choudhary | F85: Avengers | G85: =_xlfn.IFNA(VLOOKUP(B85,O:P,2,FALSE),"TBA") -> TBA | H85: ITES | I85: TBA | J85: ITES
B86: Grant Thornton payroll | D86: TBA | E86: Santhosh G | F86: Champions | G86: =_xlfn.IFNA(VLOOKUP(B86,O:P,2,FALSE),"TBA") -> TBA | H86: ITES | I86: TBA | J86: ITES
B87: Harman Non IT | D87: TBA | E87: Tamil C | G87: =_xlfn.IFNA(VLOOKUP(B87,O:P,2,FALSE),"TBA") -> TBA | H87: ITES | I87: TBA | J87: ITES
B88: Harman_Payroll | D88: TBA | E88: Tamil C | G88: =_xlfn.IFNA(VLOOKUP(B88,O:P,2,FALSE),"TBA") -> TBA | H88: ITES | I88: TBA | J88: ITES
B89: HP | D89: Monisha R | E89: Monisha R | F89: Avengers | G89: =_xlfn.IFNA(VLOOKUP(B89,O:P,2,FALSE),"TBA") -> TBA | H89: ITES | I89: Jawad Ulla Khan | J89: ITES
B90: HP- drubhajoythi | D90: Monisha R | E90: Monisha R | F90: Avengers | G90: =_xlfn.IFNA(VLOOKUP(B90,O:P,2,FALSE),"TBA") -> TBA | H90: ITES | I90: Jawad Ulla Khan | J90: ITES
B91: HP_Subramanya | D91: Monisha R | E91: Monisha R | F91: Avengers | G91: =_xlfn.IFNA(VLOOKUP(B91,O:P,2,FALSE),"TBA") -> TBA | H91: ITES | I91: Jawad Ulla Khan | J91: ITES
B92: HP-samerndra | D92: Monisha R | E92: Monisha R | F92: Avengers | G92: =_xlfn.IFNA(VLOOKUP(B92,O:P,2,FALSE),"TBA") -> TBA | H92: ITES | I92: Jawad Ulla Khan | J92: ITES
B93: HP 70 | D93: Monisha R | E93: Monisha R | F93: Avengers | G93: =_xlfn.IFNA(VLOOKUP(B93,O:P,2,FALSE),"TBA") -> TBA | H93: ITES | I93: Jawad Ulla Khan | J93: ITES
B94: Lenovo | D94: Jawad Ulla Khan | E94: t | F94: Avengers | G94: =_xlfn.IFNA(VLOOKUP(B94,O:P,2,FALSE),"TBA") -> TBA | H94: ITES | I94: UHG/Lenovo | J94: ITES
B95: Lenovo 2 | D95: Jawad Ulla Khan | E95: Prathyusha Mangalampalli | F95: Avengers | G95: =_xlfn.IFNA(VLOOKUP(B95,O:P,2,FALSE),"TBA") -> TBA | H95: ITES | I95: UHG/Lenovo | J95: ITES
B96: LTTS China-FTE | D96: TBA | E96: Pramod P | F96: Nirmit | G96: =_xlfn.IFNA(VLOOKUP(B96,O:P,2,FALSE),"TBA") -> TBA | H96: ITES | I96: TBA | J96: ITES
B97: Lumen routing | D97: Joyesh Banerjee | E97: Bijoy | F97: Anuradha | G97: =_xlfn.IFNA(VLOOKUP(B97,O:P,2,FALSE),"TBA") -> TBA | H97: ITES | I97: Anuradha | J97: ITES
B98: Lumen routing | C98: Lumen routing | D98: Joyesh Banerjee | E98: Bijoy | F98: Anuradha | G98: =_xlfn.IFNA(VLOOKUP(B98,O:P,2,FALSE),"TBA") -> TBA | H98: ITES | I98: Anuradha | J98: ITES
B99: Meolaa | D99: TBA | E99: Goutham Raj | F99: Champions | G99: =_xlfn.IFNA(VLOOKUP(B99,O:P,2,FALSE),"TBA") -> TBA | H99: ITES | I99: Jawad Ulla Khan | J99: ITES
B100: Monsanto (Bayer) - Payroll | D100: TBA | F100: Champions | G100: =_xlfn.IFNA(VLOOKUP(B100,O:P,2,FALSE),"TBA") -> TBA | H100: ITES | I100: TBA | J100: ITES
...
